pyobjectify/__init__.py
pyobjectify/_version.py
pyobjectify/pyobjectify.py
pyobjectify/tests/test_integration.py
pyobjectify/tests/test_unit.py
pyobjectify/tests/data/data.example
pyobjectify/tests/data/example.csv
pyobjectify/tests/data/example.json
pyobjectify/tests/data/example.tsv
pyobjectify/tests/data/example.xml
pyobjectify/tests/data/test.json
pyobjectify-0.1.1.dist-info/LICENSE
pyobjectify-0.1.1.dist-info/METADATA
pyobjectify-0.1.1.dist-info/WHEEL
pyobjectify-0.1.1.dist-info/top_level.txt
pyobjectify-0.1.1.dist-info/RECORD
