Metadata-Version: 2.1
Name: pyobjectify
Version: 0.1.1
Summary: Bridging the gap across the different file formats and streamlining the process to accessing ingested data via Python objects
Author-email: Raymond Wu <wu.raymond@columbia.edu>
License: MIT License
Project-URL: repository, https://github.com/wu-rymd/pyobjectify
Classifier: Development Status :: 2 - Pre-Alpha
Classifier: Programming Language :: Python :: Implementation :: CPython
Classifier: Programming Language :: Python :: Implementation :: PyPy
Classifier: Programming Language :: Python :: 3
Classifier: Programming Language :: Python :: 3.7
Classifier: Programming Language :: Python :: 3.8
Classifier: Programming Language :: Python :: 3.9
Classifier: Programming Language :: Python :: 3.10
Classifier: Programming Language :: Python :: 3.11
Requires-Python: >=3.7
License-File: LICENSE
Requires-Dist: certifi (==2022.12.7)
Requires-Dist: charset-normalizer (==3.0.1)
Requires-Dist: idna (==3.4)
Requires-Dist: requests (==2.28.2)
Requires-Dist: types-requests (==2.28.11.15)
Requires-Dist: types-xmltodict (==0.13.0.2)
Requires-Dist: urllib3 (==1.26.14)
Requires-Dist: xmltodict (==0.13.0)
Requires-Dist: numpy (==1.24.2)
Requires-Dist: pandas (==1.5.3)
Requires-Dist: python-dateutil (==2.8.2)
Requires-Dist: pytz (==2023.2)
Requires-Dist: six (==1.16.0)
Provides-Extra: develop
Requires-Dist: black (>=22) ; extra == 'develop'
Requires-Dist: bump2version (>=1.0.0) ; extra == 'develop'
Requires-Dist: check-manifest ; extra == 'develop'
Requires-Dist: flake8 (>=3.7.8) ; extra == 'develop'
Requires-Dist: flake8-black (>=0.2.1) ; extra == 'develop'
Requires-Dist: flake8-pyproject ; extra == 'develop'
Requires-Dist: mypy ; extra == 'develop'
Requires-Dist: pytest (>=4.3.0) ; extra == 'develop'
Requires-Dist: pytest-cov (>=2.6.1) ; extra == 'develop'
Requires-Dist: twine ; extra == 'develop'
Requires-Dist: wheel ; extra == 'develop'
